RTL/IF/pc.v
module pc(
    input clk,
    input wr_en,    // create stall
    input b_sel,    // branch detect
    input [31:0] b_target,
    input reset_n,    //active low
    output reg [31:0] pc,
    output [31:0] pc_4) ;

    wire [31:0] next_pc;
    assign pc_4= pc+32'd4;
    assign next_pc =(b_sel)? b_target : pc_4;

    always @(posedge clk) begin
    if (!reset_n)
        pc <= 32'b0;
    else if (wr_en)
        pc <= next_pc;
    end
    
endmodule

RTL/Test bench/tb_pc.v
`timescale 1ns/1ps

module pc_tb;

  reg         r_clk;
  reg         r_rst_n;
  reg         r_pc_write;
  reg         r_pc_sel;
  reg  [31:0] r_branch_target;
  wire [31:0] w_pc;
  wire [31:0] w_pc_plus4;

  pc dut
  (
    .clk            (r_clk),
    .reset_n          (r_rst_n),
    .wr_en       (r_pc_write),
    .b_sel         (r_pc_sel),
    .b_target  (r_branch_target),
    .pc             (w_pc),
    .pc_4      (w_pc_plus4)
  );

  // Clock: 10ns period 
  initial r_clk = 1'b0;
  always #5 r_clk = ~r_clk;

  initial // intial means at time 0
  begin

    // Reset
    r_rst_n         = 1'b0;
    r_pc_write      = 1'b1;
    r_pc_sel        = 1'b0;
    r_branch_target = 32'h0000_0000;
    @(posedge r_clk);// wait until pos edge
    @(posedge r_clk);
    r_rst_n = 1'b1;

    // Sequential fetch: PC should step +4 each cycle (0,4,8,C,10)
    repeat (4) @(posedge r_clk);

    // Stall: for 2 cycles 
    r_pc_write = 1'b0;
    repeat (2) @(posedge r_clk);
    r_pc_write = 1'b1;

    // Branch resolved 
    r_pc_sel        = 1'b1;
    r_branch_target = 32'h0000_0040;
    @(posedge r_clk);
    r_pc_sel = 1'b0;

    // Resume sequential fetch from the branch target
    repeat (4) @(posedge r_clk);

    $display("Final PC = %h", w_pc);
    $finish;
  end

  always @(posedge r_clk)
    $display("t=%0t  rst_n=%b  pc_write=%b  pc_sel=%b  PC=%h  PC+4=%h",
              $time, r_rst_n, r_pc_write, r_pc_sel, w_pc, w_pc_plus4);

endmodule

msim/pc_wave.vcd
$date
	Thu Jun 18 15:59:15 2026
$end
$version
	ModelSim Version 2020.1
$end
$timescale
	1ps
$end

$scope module pc_tb $end
$var reg 1 ! r_clk $end
$var reg 1 " r_rst_n $end
$var reg 1 # r_pc_write $end
$var reg 1 $ r_pc_sel $end
$var reg 32 % r_branch_target [31:0] $end
$var wire 1 & w_pc [31] $end
$var wire 1 ' w_pc [30] $end
$var wire 1 ( w_pc [29] $end
$var wire 1 ) w_pc [28] $end
$var wire 1 * w_pc [27] $end
$var wire 1 + w_pc [26] $end
$var wire 1 , w_pc [25] $end
$var wire 1 - w_pc [24] $end
$var wire 1 . w_pc [23] $end
$var wire 1 / w_pc [22] $end
$var wire 1 0 w_pc [21] $end
$var wire 1 1 w_pc [20] $end
$var wire 1 2 w_pc [19] $end
$var wire 1 3 w_pc [18] $end
$var wire 1 4 w_pc [17] $end
$var wire 1 5 w_pc [16] $end
$var wire 1 6 w_pc [15] $end
$var wire 1 7 w_pc [14] $end
$var wire 1 8 w_pc [13] $end
$var wire 1 9 w_pc [12] $end
$var wire 1 : w_pc [11] $end
$var wire 1 ; w_pc [10] $end
$var wire 1 < w_pc [9] $end
$var wire 1 = w_pc [8] $end
$var wire 1 > w_pc [7] $end
$var wire 1 ? w_pc [6] $end
$var wire 1 @ w_pc [5] $end
$var wire 1 A w_pc [4] $end
$var wire 1 B w_pc [3] $end
$var wire 1 C w_pc [2] $end
$var wire 1 D w_pc [1] $end
$var wire 1 E w_pc [0] $end
$var wire 1 F w_pc_plus4 [31] $end
$var wire 1 G w_pc_plus4 [30] $end
$var wire 1 H w_pc_plus4 [29] $end
$var wire 1 I w_pc_plus4 [28] $end
$var wire 1 J w_pc_plus4 [27] $end
$var wire 1 K w_pc_plus4 [26] $end
$var wire 1 L w_pc_plus4 [25] $end
$var wire 1 M w_pc_plus4 [24] $end
$var wire 1 N w_pc_plus4 [23] $end
$var wire 1 O w_pc_plus4 [22] $end
$var wire 1 P w_pc_plus4 [21] $end
$var wire 1 Q w_pc_plus4 [20] $end
$var wire 1 R w_pc_plus4 [19] $end
$var wire 1 S w_pc_plus4 [18] $end
$var wire 1 T w_pc_plus4 [17] $end
$var wire 1 U w_pc_plus4 [16] $end
$var wire 1 V w_pc_plus4 [15] $end
$var wire 1 W w_pc_plus4 [14] $end
$var wire 1 X w_pc_plus4 [13] $end
$var wire 1 Y w_pc_plus4 [12] $end
$var wire 1 Z w_pc_plus4 [11] $end
$var wire 1 [ w_pc_plus4 [10] $end
$var wire 1 \ w_pc_plus4 [9] $end
$var wire 1 ] w_pc_plus4 [8] $end
$var wire 1 ^ w_pc_plus4 [7] $end
$var wire 1 _ w_pc_plus4 [6] $end
$var wire 1 ` w_pc_plus4 [5] $end
$var wire 1 a w_pc_plus4 [4] $end
$var wire 1 b w_pc_plus4 [3] $end
$var wire 1 c w_pc_plus4 [2] $end
$var wire 1 d w_pc_plus4 [1] $end
$var wire 1 e w_pc_plus4 [0] $end

$scope module dut $end
$var wire 1 f clk $end
$var wire 1 g wr_en $end
$var wire 1 h b_sel $end
$var wire 1 i b_target [31] $end
$var wire 1 j b_target [30] $end
$var wire 1 k b_target [29] $end
$var wire 1 l b_target [28] $end
$var wire 1 m b_target [27] $end
$var wire 1 n b_target [26] $end
$var wire 1 o b_target [25] $end
$var wire 1 p b_target [24] $end
$var wire 1 q b_target [23] $end
$var wire 1 r b_target [22] $end
$var wire 1 s b_target [21] $end
$var wire 1 t b_target [20] $end
$var wire 1 u b_target [19] $end
$var wire 1 v b_target [18] $end
$var wire 1 w b_target [17] $end
$var wire 1 x b_target [16] $end
$var wire 1 y b_target [15] $end
$var wire 1 z b_target [14] $end
$var wire 1 { b_target [13] $end
$var wire 1 | b_target [12] $end
$var wire 1 } b_target [11] $end
$var wire 1 ~ b_target [10] $end
$var wire 1 !! b_target [9] $end
$var wire 1 "! b_target [8] $end
$var wire 1 #! b_target [7] $end
$var wire 1 $! b_target [6] $end
$var wire 1 %! b_target [5] $end
$var wire 1 &! b_target [4] $end
$var wire 1 '! b_target [3] $end
$var wire 1 (! b_target [2] $end
$var wire 1 )! b_target [1] $end
$var wire 1 *! b_target [0] $end
$var wire 1 +! reset_n $end
$var reg 32 ,! pc [31:0] $end
$var wire 1 F pc_4 [31] $end
$var wire 1 G pc_4 [30] $end
$var wire 1 H pc_4 [29] $end
$var wire 1 I pc_4 [28] $end
$var wire 1 J pc_4 [27] $end
$var wire 1 K pc_4 [26] $end
$var wire 1 L pc_4 [25] $end
$var wire 1 M pc_4 [24] $end
$var wire 1 N pc_4 [23] $end
$var wire 1 O pc_4 [22] $end
$var wire 1 P pc_4 [21] $end
$var wire 1 Q pc_4 [20] $end
$var wire 1 R pc_4 [19] $end
$var wire 1 S pc_4 [18] $end
$var wire 1 T pc_4 [17] $end
$var wire 1 U pc_4 [16] $end
$var wire 1 V pc_4 [15] $end
$var wire 1 W pc_4 [14] $end
$var wire 1 X pc_4 [13] $end
$var wire 1 Y pc_4 [12] $end
$var wire 1 Z pc_4 [11] $end
$var wire 1 [ pc_4 [10] $end
$var wire 1 \ pc_4 [9] $end
$var wire 1 ] pc_4 [8] $end
$var wire 1 ^ pc_4 [7] $end
$var wire 1 _ pc_4 [6] $end
$var wire 1 ` pc_4 [5] $end
$var wire 1 a pc_4 [4] $end
$var wire 1 b pc_4 [3] $end
$var wire 1 c pc_4 [2] $end
$var wire 1 d pc_4 [1] $end
$var wire 1 e pc_4 [0] $end
$var wire 1 -! next_pc [31] $end
$var wire 1 .! next_pc [30] $end
$var wire 1 /! next_pc [29] $end
$var wire 1 0! next_pc [28] $end
$var wire 1 1! next_pc [27] $end
$var wire 1 2! next_pc [26] $end
$var wire 1 3! next_pc [25] $end
$var wire 1 4! next_pc [24] $end
$var wire 1 5! next_pc [23] $end
$var wire 1 6! next_pc [22] $end
$var wire 1 7! next_pc [21] $end
$var wire 1 8! next_pc [20] $end
$var wire 1 9! next_pc [19] $end
$var wire 1 :! next_pc [18] $end
$var wire 1 ;! next_pc [17] $end
$var wire 1 <! next_pc [16] $end
$var wire 1 =! next_pc [15] $end
$var wire 1 >! next_pc [14] $end
$var wire 1 ?! next_pc [13] $end
$var wire 1 @! next_pc [12] $end
$var wire 1 A! next_pc [11] $end
$var wire 1 B! next_pc [10] $end
$var wire 1 C! next_pc [9] $end
$var wire 1 D! next_pc [8] $end
$var wire 1 E! next_pc [7] $end
$var wire 1 F! next_pc [6] $end
$var wire 1 G! next_pc [5] $end
$var wire 1 H! next_pc [4] $end
$var wire 1 I! next_pc [3] $end
$var wire 1 J! next_pc [2] $end
$var wire 1 K! next_pc [1] $end
$var wire 1 L! next_pc [0] $end
$upscope $end
$upscope $end
$enddefinitions $end
#0
$dumpvars
0!
0"
1#
0$
b0 %
bx ,!
xE
xD
xC
xB
xA
x@
x?
x>
x=
x<
x;
x:
x9
x8
x7
x6
x5
x4
x3
x2
x1
x0
x/
x.
x-
x,
x+
x*
x)
x(
x'
x&
xe
xd
xc
xb
xa
x`
x_
x^
x]
x\
x[
xZ
xY
xX
xW
xV
xU
xT
xS
xR
xQ
xP
xO
xN
xM
xL
xK
xJ
xI
xH
xG
xF
xL!
xK!
xJ!
xI!
xH!
xG!
xF!
xE!
xD!
xC!
xB!
xA!
x@!
x?!
x>!
x=!
x<!
x;!
x:!
x9!
x8!
x7!
x6!
x5!
x4!
x3!
x2!
x1!
x0!
x/!
x.!
x-!
0*!
0)!
0(!
0'!
0&!
0%!
0$!
0#!
0"!
0!!
0~
0}
0|
0{
0z
0y
0x
0w
0v
0u
0t
0s
0r
0q
0p
0o
0n
0m
0l
0k
0j
0i
0h
1g
0+!
0f
$end
#5000
1!
1f
b0 ,!
0E
0D
0C
0B
0A
0@
0?
0>
0=
0<
0;
0:
09
08
07
06
05
04
03
02
01
00
0/
0.
0-
0,
0+
0*
0)
0(
0'
0&
0e
0d
1c
0b
0a
0`
0_
0^
0]
0\
0[
0Z
0Y
0X
0W
0V
0U
0T
0S
0R
0Q
0P
0O
0N
0M
0L
0K
0J
0I
0H
0G
0F
0L!
0K!
1J!
0I!
0H!
0G!
0F!
0E!
0D!
0C!
0B!
0A!
0@!
0?!
0>!
0=!
0<!
0;!
0:!
09!
08!
07!
06!
05!
04!
03!
02!
01!
00!
0/!
0.!
0-!
#10000
0!
0f
#15000
1!
1f
1"
1+!
#20000
0!
0f
#25000
1!
1f
b100 ,!
1C
0c
1b
0J!
1I!
#30000
0!
0f
#35000
1!
1f
b1000 ,!
0C
1B
1c
1J!
#40000
0!
0f
#45000
1!
1f
b1100 ,!
1C
0c
0b
1a
0J!
0I!
1H!
#50000
0!
0f
#55000
1!
1f
0#
0g
b10000 ,!
0C
0B
1A
1c
1J!
#60000
0!
0f
#65000
1!
1f
#70000
0!
0f
#75000
1!
1f
1#
1$
b1000000 %
1g
1h
1$!
0J!
0H!
1F!
#80000
0!
0f
#85000
1!
1f
0$
0h
1J!
1H!
0F!
b1000000 ,!
0A
1?
0a
1_
0H!
1F!
#90000
0!
0f
#95000
1!
1f
b1000100 ,!
1C
0c
1b
0J!
1I!
#100000
0!
0f
#105000
1!
1f
b1001000 ,!
0C
1B
1c
1J!
#110000
0!
0f
#115000
1!
1f
b1001100 ,!
1C
0c
0b
1a
0J!
0I!
1H!
